aced_submission/__init__.py
aced_submission/cli.py
aced_submission/fhir_store.py
aced_submission/gen_validator.py
aced_submission/meta.py
aced_submission/meta_discovery_load.py
aced_submission/meta_flat_load.py
aced_submission/meta_graph_load.py
aced_submission/pelican.py
aced_submission/uploader.py
aced_submission/util.py
aced_submission/validator.py
tests/integration/__init__.py
tests/integration/conftest.py
tests/integration/test_upload.py
tests/unit/__init__.py
tests/unit/conftest.py
tests/unit/test_coding_conventions.py
aced_submission-0.0.7.dist-info/METADATA
aced_submission-0.0.7.dist-info/WHEEL
aced_submission-0.0.7.dist-info/entry_points.txt
aced_submission-0.0.7.dist-info/top_level.txt
aced_submission-0.0.7.dist-info/RECORD
