Metadata-Version: 2.1
Name: aced-submission
Version: 0.0.7
Summary: Populate ACED commons from FHIR resources
Home-page: https://github.com/ACED-IDP/aced_submission
Author: compbio
License: UNKNOWN
Project-URL: Bug Reports, https://github.com/ACED-IDP/aced_submission/issues
Project-URL: Source, https://github.com/ACED-IDP/aced_submission
Keywords: gen3 bioinformatics
Platform: UNKNOWN
Classifier: Development Status :: 3 - Alpha
Classifier: Intended Audience :: Developers
Classifier: Topic :: Software Development :: Build Tools
Classifier: License :: OSI Approved :: MIT License
Classifier: Programming Language :: Python :: 3.9
Requires-Python: >=3.6, <4
Requires-Dist: click
Requires-Dist: orjson
Requires-Dist: inflection
Requires-Dist: gen3
Requires-Dist: fhir.resources
Requires-Dist: PyJWT
Requires-Dist: python-magic
Requires-Dist: tqdm
Requires-Dist: requests
Requires-Dist: pydantic
Requires-Dist: joblib
Requires-Dist: beautifulsoup4
Requires-Dist: psycopg2-binary
Requires-Dist: elasticsearch <7.14.0
Requires-Dist: dictionaryutils
Requires-Dist: gen3datamodel <3.0.2
